nprimos/nºprimos.py
primos-1.0.dist-info/LICENSE
primos-1.0.dist-info/METADATA
primos-1.0.dist-info/WHEEL
primos-1.0.dist-info/top_level.txt
primos-1.0.dist-info/RECORD
