Metadata-Version: 2.1
Name: primos
Version: 1.0
Summary: A tool to know if is a prime number
Home-page: UNKNOWN
Author: Enrique Sánchez
Author-email: enriquesanchezgalan1998@gmail.com
License: GNU GPLv3
Keywords: prime number
Platform: UNKNOWN
Classifier: Development Status :: 4 - Beta
Classifier: Intended Audience :: Developers
Classifier: Topic :: Utilities
Classifier: License :: OSI Approved :: GNU General Public License v3 (GPLv3)
Classifier: Programming Language :: Python :: 3
Classifier: Operating System :: OS Independent
